jtune/__init__.py
jtune/jtune.py
jtune-4.0.1.dist-info/LICENSE
jtune-4.0.1.dist-info/METADATA
jtune-4.0.1.dist-info/WHEEL
jtune-4.0.1.dist-info/entry_points.txt
jtune-4.0.1.dist-info/top_level.txt
jtune-4.0.1.dist-info/RECORD
